License.txt
MANIFEST.in
README.txt
setup.cfg
setup.py
EnhAtts.egg-info/PKG-INFO
EnhAtts.egg-info/SOURCES.txt
EnhAtts.egg-info/dependency_links.txt
EnhAtts.egg-info/requires.txt
EnhAtts.egg-info/top_level.txt
EnhAtts.egg-info/zip-safe
enhatts/__init__.py
enhatts/_descriptors.py
enhatts/_fields.py