Metadata-Version: 1.1
Name: EnhAtts
Version: 0.1.0
Summary: Ordered attributes with a powerful API.
Home-page: http://github.com/IvIePhisto/EnhAtts
Author: Michael Pohl
Author-email: pohl-michael@gmx.biz
License: MIT
Keywords: attributes fields validation atomicity
Platform: UNKNOWN
Classifier: Development Status :: 4 - Beta
Classifier: Intended Audience :: Developers
Classifier: License :: OSI Approved :: MIT License
Classifier: Programming Language :: Python :: 2.7
Classifier: Programming Language :: Python :: 3.3
Classifier: Topic :: Software Development
